online_mean.py
online_mean-2023.1.1.dist-info/LICENSE
online_mean-2023.1.1.dist-info/WHEEL
online_mean-2023.1.1.dist-info/METADATA
online_mean-2023.1.1.dist-info/RECORD
